effort_sharing-2025.8.1.dist-info/licenses/LICENSE
effortsharing/__init__.py
effortsharing/cache.py
effortsharing/cli.py
effortsharing/config.py
effortsharing/exports.py
effortsharing/save.py
effortsharing/allocation/__init__.py
effortsharing/allocation/ap.py
effortsharing/allocation/ecpc.py
effortsharing/allocation/gdr.py
effortsharing/allocation/gf.py
effortsharing/allocation/pc.py
effortsharing/allocation/pcb.py
effortsharing/allocation/pcc.py
effortsharing/allocation/utils.py
effortsharing/allocations/allocation_combinedapproaches.py
effortsharing/country_specific/__init__.py
effortsharing/country_specific/netherlands.py
effortsharing/country_specific/norway.py
effortsharing/input/__init__.py
effortsharing/input/all.py
effortsharing/input/emissions.py
effortsharing/input/ndcs.py
effortsharing/input/policyscens.py
effortsharing/input/socioeconomics.py
effortsharing/pathways/co2_trajectories.py
effortsharing/pathways/global_budgets.py
effortsharing/pathways/global_pathways.py
effortsharing/pathways/nonco2.py
effortsharing/postanalysis/tempalign.py
effortsharing/postanalysis/variancedecomp.py
effort_sharing-2025.8.1.dist-info/METADATA
effort_sharing-2025.8.1.dist-info/WHEEL
effort_sharing-2025.8.1.dist-info/entry_points.txt
effort_sharing-2025.8.1.dist-info/top_level.txt
effort_sharing-2025.8.1.dist-info/RECORD
