Metadata-Version: 2.4
Name: effort-sharing
Version: 2025.8.1
Summary: Analyse countries' emission allocations based on various effort-sharing principles.
Maintainer-email: Mark Dekker <Mark.Dekker@pbl.nl>
License-Expression: MIT
Project-URL: Source, https://github.com/imagepbl/effort-sharing
Project-URL: Repository, https://github.com/imagepbl/effort-sharing
Project-URL: Issues, https://github.com/imagepbl/effort-sharing/issues
Project-URL: Explorer, https://www.carbonbudgetexplorer.eu
Keywords: fair shares,carbon budget,emission allocations,effort sharing
Requires-Python: >=3.12
License-File: LICENSE
Requires-Dist: cyclopts
Requires-Dist: h5netcdf
Requires-Dist: netcdf4
Requires-Dist: numpy
Requires-Dist: openpyxl
Requires-Dist: pandas
Requires-Dist: kaleido
Requires-Dist: pyyaml
Requires-Dist: rich
Requires-Dist: SALib
Requires-Dist: tqdm
Requires-Dist: xarray
Requires-Dist: country-converter
Provides-Extra: dev
Requires-Dist: ruff; extra == "dev"
Requires-Dist: uv; extra == "dev"
Requires-Dist: pytest; extra == "dev"
Dynamic: license-file
